tesdaq/__init__.py
tesdaq/command.py
tesdaq/constants.py
tesdaq/query.py
tesdaq/listen/__init__.py
tesdaq/listen/ni.py
tesdaq/task/__init__.py
tesdaq/task/serialize.py
tesdaq-0.0.11.dist-info/METADATA
tesdaq-0.0.11.dist-info/WHEEL
tesdaq-0.0.11.dist-info/top_level.txt
tesdaq-0.0.11.dist-info/RECORD
