Metadata-Version: 2.1
Name: tesdaq
Version: 0.0.11
Summary: DAQ Control using Redis as a message broker.
Home-page: https://github.com/ucbpylegroup/tesdaq
Author: Connor Duncan
Author-email: ctdunc@berkeley.edu
License: UNKNOWN
Platform: UNKNOWN
Classifier: Development Status :: 2 - Pre-Alpha
Classifier: Programming Language :: Python :: 3
Classifier: License :: OSI Approved :: MIT License
Classifier: Operating System :: POSIX :: Linux
Classifier: Topic :: Scientific/Engineering :: Physics
Classifier: Intended Audience :: Science/Research
Requires-Dist: numpy (==1.16.4)
Requires-Dist: redis (==3.2.1)
